python_sri/__init__.py
python_sri/parser.py
python_sri/py.typed
python_sri/sri.py
python_sri-0.2.0.dist-info/licenses/LICENSE
python_sri-0.2.0.dist-info/METADATA
python_sri-0.2.0.dist-info/WHEEL
python_sri-0.2.0.dist-info/top_level.txt
python_sri-0.2.0.dist-info/RECORD
