Metadata-Version: 2.4
Name: python_sri
Version: 0.2.0
Summary: Generate SRI hashes on the fly for some HTML, files, URL or data
Author-email: lv_oz2 <lv_oz2@icloud.com>
License-Expression: MIT
Project-URL: Homepage, https://github.com/lvoz2/python_sri
Project-URL: Issues, https://github.com/lvoz2/python_sri/issues
Project-URL: Documentation, https://github.com/lvoz2/python_sri/wiki
Keywords: sri,subresource integrity
Classifier: Operating System :: OS Independent
Classifier: Programming Language :: Python :: 3.10
Classifier: Programming Language :: Python :: 3.11
Classifier: Programming Language :: Python :: 3.12
Classifier: Programming Language :: Python :: 3.13
Classifier: Programming Language :: Python :: 3.14
Classifier: Programming Language :: Python :: Free Threading
Classifier: Topic :: Internet :: WWW/HTTP
Classifier: Topic :: Internet :: WWW/HTTP :: HTTP Servers
Classifier: Topic :: Internet :: WWW/HTTP :: Site Management
Classifier: Topic :: Security
Classifier: Topic :: Security :: Cryptography
Classifier: Typing :: Typed
Requires-Python: >=3.10
License-File: LICENSE
Dynamic: license-file
